TensorflowShenduXuexiShizhanZhinanZhongwenbanChuyiFix1/README.md
TensorflowShenduXuexiShizhanZhinanZhongwenbanChuyiFix1/__init__.py
TensorflowShenduXuexiShizhanZhinanZhongwenbanChuyiFix1/__main__.py
TensorflowShenduXuexiShizhanZhinanZhongwenbanChuyiFix1/file.epub
TensorflowShenduXuexiShizhanZhinanZhongwenbanChuyiFix1/index.html
TensorflowShenduXuexiShizhanZhinanZhongwenbanChuyiFix1/css/__init__.py
TensorflowShenduXuexiShizhanZhinanZhongwenbanChuyiFix1/css/annotations.css
TensorflowShenduXuexiShizhanZhinanZhongwenbanChuyiFix1/css/main.css
TensorflowShenduXuexiShizhanZhinanZhongwenbanChuyiFix1/css/normalize.css
TensorflowShenduXuexiShizhanZhinanZhongwenbanChuyiFix1/css/popup.css
TensorflowShenduXuexiShizhanZhinanZhongwenbanChuyiFix1/font/__init__.py
TensorflowShenduXuexiShizhanZhinanZhongwenbanChuyiFix1/font/fontello.eot
TensorflowShenduXuexiShizhanZhinanZhongwenbanChuyiFix1/font/fontello.svg
TensorflowShenduXuexiShizhanZhinanZhongwenbanChuyiFix1/font/fontello.ttf
TensorflowShenduXuexiShizhanZhinanZhongwenbanChuyiFix1/font/fontello.woff
TensorflowShenduXuexiShizhanZhinanZhongwenbanChuyiFix1/img/__init__.py
TensorflowShenduXuexiShizhanZhinanZhongwenbanChuyiFix1/img/annotator-glyph-sprite.png
TensorflowShenduXuexiShizhanZhinanZhongwenbanChuyiFix1/img/annotator-icon-sprite.png
TensorflowShenduXuexiShizhanZhinanZhongwenbanChuyiFix1/img/apple-touch-icon.png
TensorflowShenduXuexiShizhanZhinanZhongwenbanChuyiFix1/img/cancelfullscreen.png
TensorflowShenduXuexiShizhanZhinanZhongwenbanChuyiFix1/img/close.png
TensorflowShenduXuexiShizhanZhinanZhongwenbanChuyiFix1/img/fullscreen.png
TensorflowShenduXuexiShizhanZhinanZhongwenbanChuyiFix1/img/loader.gif
TensorflowShenduXuexiShizhanZhinanZhongwenbanChuyiFix1/img/menu-icon.png
TensorflowShenduXuexiShizhanZhinanZhongwenbanChuyiFix1/img/save.png
TensorflowShenduXuexiShizhanZhinanZhongwenbanChuyiFix1/img/saved.png
TensorflowShenduXuexiShizhanZhinanZhongwenbanChuyiFix1/img/settings-s.png
tensorflow_shendu_xuexi_shizhan_zhinan_zhongwenban_chuyi_fix1-2025.3.24.1.dist-info/METADATA
tensorflow_shendu_xuexi_shizhan_zhinan_zhongwenban_chuyi_fix1-2025.3.24.1.dist-info/WHEEL
tensorflow_shendu_xuexi_shizhan_zhinan_zhongwenban_chuyi_fix1-2025.3.24.1.dist-info/entry_points.txt
tensorflow_shendu_xuexi_shizhan_zhinan_zhongwenban_chuyi_fix1-2025.3.24.1.dist-info/top_level.txt
tensorflow_shendu_xuexi_shizhan_zhinan_zhongwenban_chuyi_fix1-2025.3.24.1.dist-info/RECORD
